pelican/plugins/pelican_lunr/__init__.py
pelican_lunr-0.3.0.dist-info/licenses/LICENSE.txt
pelican_lunr-0.3.0.dist-info/METADATA
pelican_lunr-0.3.0.dist-info/WHEEL
pelican_lunr-0.3.0.dist-info/top_level.txt
pelican_lunr-0.3.0.dist-info/RECORD
